objective_weighting/__init__.py
objective_weighting/additions.py
objective_weighting/correlations.py
objective_weighting/normalizations.py
objective_weighting/weighting_methods.py
objective_weighting/mcda_methods/__init__.py
objective_weighting/mcda_methods/mcda_method.py
objective_weighting/mcda_methods/mcda_method_smaa.py
objective_weighting/mcda_methods/vikor.py
objective_weighting/mcda_methods/vikor_smaa.py
objective_weighting-0.1.8.dist-info/LICENSE
objective_weighting-0.1.8.dist-info/METADATA
objective_weighting-0.1.8.dist-info/WHEEL
objective_weighting-0.1.8.dist-info/top_level.txt
objective_weighting-0.1.8.dist-info/RECORD
